MANIFEST.in
setup.py
avi/__init__.py
avi/sdk/__init__.py
avi/sdk/avi_api.py
avi/sdk/avi_sdk.py
avi/sdk/csp_avi_api.py
avi/sdk/saml_avi_api.py
avi/sdk/setup.cfg
avi/sdk/setup.py
avi/sdk/samples/__init__.py
avi/sdk/samples/alb_rules.py
avi/sdk/samples/avi_config_backup.py
avi/sdk/samples/change_password_example.py
avi/sdk/samples/clone_vs.py
avi/sdk/samples/clone_vs_segroup.py
avi/sdk/samples/common.py
avi/sdk/samples/custom_dns_script_infoblox.py
avi/sdk/samples/custom_ipam_script_infoblox.py
avi/sdk/samples/get_config_logs.py
avi/sdk/samples/inventory_example.py
avi/sdk/samples/multi_tenant.py
avi/sdk/samples/operstate_controlscript_infoblox.py
avi/sdk/samples/patch_api_example.py
avi/sdk/samples/se_vs_metrics.py
avi/sdk/samples/simple_control_script.py
avi/sdk/samples/ssl_keyandcertificate_w_altnames.py
avi/sdk/samples/sticky_pool_group.py
avi/sdk/samples/validate_custom_ipam_script.py
avi/sdk/samples/virtualservice_disable.py
avi/sdk/samples/virtualservice_examples_api.py
avi/sdk/samples/virtualservice_examples_saml_api.py
avi/sdk/samples/virtualservice_examples_sdk.py
avi/sdk/samples/apic/AddBDSubnet.xml
avi/sdk/samples/apic/AddEPGContractCons.xml
avi/sdk/samples/apic/AddEPGContractProv.xml
avi/sdk/samples/apic/CreateBD.xml
avi/sdk/samples/apic/CreateContract.xml
avi/sdk/samples/apic/CreateEPG.xml
avi/sdk/samples/apic/CreateGraphWithParams.xml
avi/sdk/samples/apic/CreateTenant.xml
avi/sdk/samples/apic/__init__.py
avi/sdk/samples/apic/apic_client.py
avi/sdk/samples/apic/apic_tenant.py
avi/sdk/samples/apic/apic_tenant_config.json
avi/sdk/samples/certs/cacert.pem
avi/sdk/samples/certs/cakey.pem
avi/sdk/samples/certs/server.crt
avi/sdk/samples/certs/server.key
avi/sdk/samples/heat/lb-asg.yaml
avi/sdk/samples/heat/lb-env.yaml
avi/sdk/samples/heat/lb-server.yaml
avi/sdk/samples/init_system/__init__.py
avi/sdk/samples/init_system/init_system.py
avi/sdk/samples/init_system/examples/init-apic.json
avi/sdk/samples/init_system/examples/init-openstack.json
avisdk.egg-info/PKG-INFO
avisdk.egg-info/SOURCES.txt
avisdk.egg-info/dependency_links.txt
avisdk.egg-info/requires.txt
avisdk.egg-info/top_level.txt