Metadata-Version: 1.1
Name: avisdk
Version: 31.2.1
Summary: Avi python API SDK for Avi Controller REST API with samples and, utilities
Home-page: https://github.com/vmware/alb-sdk
Author: Avi Networks
Author-email: avisdk@avinetworks.com
License: Avi Networks
Keywords: AVI ADC Loadbalancer automation datacenter SDK
Platform: UNKNOWN
Classifier: Development Status :: 5 - Production/Stable
Classifier: Intended Audience :: Developers
Classifier: Operating System :: OS Independent
Classifier: Programming Language :: Python
Classifier: Programming Language :: Python :: 2.7
Classifier: Topic :: Internet :: WWW/HTTP
Classifier: Topic :: Internet :: WWW/HTTP :: Dynamic Content
